{
  "__type__": "cc.SpriteFrame",
  "content": {
    "name": "spikes (7)",
    "atlas": "e93fd8b9-51f6-4e0f-8f0d-3f563a0762a2",
    "rect": {
      "x": 0,
      "y": 0,
      "width": 320,
      "height": 320
    },
    "offset": {
      "x": 0,
      "y": 0
    },
    "originalSize": {
      "width": 320,
      "height": 320
    },
    "rotated": false,
    "capInsets": [
      0,
      0,
      0,
      0
    ],
    "texture": "89bdadaa-c90d-43bb-a52a-12e2052a16bf@6c48a",
    "packable": true
  }
}